django_cookies_samesite/__init__.py
django_cookies_samesite/middleware.py
django_cookies_samesite/models.py
django_cookies_samesite_fork-0.2.1.dist-info/AUTHORS.rst
django_cookies_samesite_fork-0.2.1.dist-info/LICENSE
django_cookies_samesite_fork-0.2.1.dist-info/METADATA
django_cookies_samesite_fork-0.2.1.dist-info/WHEEL
django_cookies_samesite_fork-0.2.1.dist-info/top_level.txt
django_cookies_samesite_fork-0.2.1.dist-info/RECORD
