Metadata-Version: 2.1
Name: django-cookies-samesite-fork
Version: 0.2.1
Summary: Middleware which sets SameSite flag for session and csrf cookies in legacy versions of Django. Forked from https://pypi.org/project/django-cookies-samesite/
Home-page: https://github.com/SALTISES4/django-cookies-samesite
Author: Antoine Lefebvre-Brossard
Author-email: antoine@protonmail.com
License: UNKNOWN
Keywords: django-cookies-samesite
Platform: UNKNOWN
Classifier: Development Status :: 3 - Alpha
Classifier: Framework :: Django :: 1.11
Classifier: Intended Audience :: Developers
Classifier: Natural Language :: English
Classifier: Programming Language :: Python :: 2
Classifier: Programming Language :: Python :: 2.7
Classifier: Programming Language :: Python :: 3
Classifier: Programming Language :: Python :: 3.6
Classifier: Programming Language :: Python :: 3.7
